green_agent/Icon
green_agent/__init__.py
green_agent/agents/Icon
green_agent/agents/__init__.py
green_agent/agents/base.py
green_agent/agents/openai_agent.py
green_agent/agents/vertexai_agent.py
green_agent/uis/Icon
green_agent/uis/__init__.py
green_agent/uis/nb.py
green_agent-0.4.0.dist-info/METADATA
green_agent-0.4.0.dist-info/WHEEL
green_agent-0.4.0.dist-info/RECORD
