Metadata-Version: 2.1
Name: green-agent
Version: 0.4.0
Summary: 
Home-page: https://github.com/NeuronQ/green-agent
Author: Andrei Anton
Author-email: io@neuronq.ro
Requires-Python: >=3.9
Classifier: Programming Language :: Python :: 3
Classifier: Programming Language :: Python :: 3.9
Classifier: Programming Language :: Python :: 3.10
Classifier: Programming Language :: Python :: 3.11
Requires-Dist: google-cloud-aiplatform (>=1.34.0,<2.0.0)
Requires-Dist: markdown (>=3.5,<4.0)
Requires-Dist: openai (>=0.28.1,<0.29.0)
Requires-Dist: python-dotenv (>=1.0.0,<2.0.0)
Project-URL: Repository, https://github.com/NeuronQ/green-agent
